pyralgen/__init__.py
pyralgen/__main__.py
pyralgen/generator.py
pyralgen/rdl/example.rdl
pyralgen/templates/main.sv
pyralgen/templates/top_include.svh
pyralgen/templates/top_pkg.sv
pyralgen/templates/uvm_reg.sv
pyralgen/templates/uvm_reg_block.sv
pyralgen-1.0.1.dist-info/licenses/LICENSE
pyralgen-1.0.1.dist-info/METADATA
pyralgen-1.0.1.dist-info/WHEEL
pyralgen-1.0.1.dist-info/entry_points.txt
pyralgen-1.0.1.dist-info/top_level.txt
pyralgen-1.0.1.dist-info/RECORD
