Metadata-Version: 2.4
Name: pyralgen
Version: 1.0.1
Summary: Python based UVM-RAL generator
Author: Ciro Bermudez
License-Expression: MIT
Project-URL: Homepage, https://github.com/cirofabianbermudez/pyralgen
Requires-Python: >=3.9
License-File: LICENSE
Requires-Dist: peakrdl-uvm>=2.3.0
Dynamic: license-file
